aioauth_client/__init__.py
aioauth_client/py.typed
aioauth_client/types.py
aioauth_client-0.30.1.dist-info/LICENSE
aioauth_client-0.30.1.dist-info/METADATA
aioauth_client-0.30.1.dist-info/WHEEL
aioauth_client-0.30.1.dist-info/RECORD
