Metadata-Version: 2.3
Name: aioauth-client
Version: 0.30.1
Summary: OAuth support for Asyncio/Trio libraries
License: MIT
Keywords: asyncio,trio,oauth
Author: Kirill Klenov
Author-email: horneds@gmail.com
Requires-Python: >=3.9,<4.0
Classifier: Development Status :: 5 - Production/Stable
Classifier: Intended Audience :: Developers
Classifier: License :: OSI Approved :: MIT License
Classifier: Programming Language :: Python
Classifier: Programming Language :: Python :: 3
Classifier: Programming Language :: Python :: 3.9
Classifier: Programming Language :: Python :: 3.10
Classifier: Programming Language :: Python :: 3.11
Classifier: Programming Language :: Python :: 3.12
Classifier: Programming Language :: Python :: 3.13
Classifier: Topic :: Internet :: WWW/HTTP
Classifier: Topic :: Software Development :: Libraries :: Python Modules
Requires-Dist: httpx
Project-URL: Homepage, https://github.com/klen/aioauth-client
Project-URL: Repository, https://github.com/klen/aioauth-client
